<annotation verified="yes">
    <folder>Annotation</folder>
    <filename>288.jpg</filename>
    <path>Pothole-Pascal-PascalVOC-export/Annotations/288.jpg</path>
    <source>
        <database>Unknown</database>
    </source>
    <size>
        <width>400</width>
        <height>225</height>
        <depth>3</depth>
    </size>
    <segmented>0</segmented>
    <object>
    <name>Pothole</name>
    <pose>Unspecified</pose>
    <truncated>0</truncated>
    <difficult>0</difficult>
    <bndbox>
        <xmin>5.096593591052713</xmin>
        <ymin>87.21732089394017</ymin>
        <xmax>399.5067817509248</xmax>
        <ymax>225</ymax>
    </bndbox>
</object>
</annotation>
