<annotation verified="yes">
    <folder>Annotation</folder>
    <filename>47.jpg</filename>
    <path>Pothole-Pascal-PascalVOC-export/Annotations/47.jpg</path>
    <source>
        <database>Unknown</database>
    </source>
    <size>
        <width>300</width>
        <height>225</height>
        <depth>3</depth>
    </size>
    <segmented>0</segmented>
    <object>
    <name>Pothole</name>
    <pose>Unspecified</pose>
    <truncated>0</truncated>
    <difficult>0</difficult>
    <bndbox>
        <xmin>71.34308916457155</xmin>
        <ymin>69.94681256882687</ymin>
        <xmax>230.38563829787233</xmax>
        <ymax>194.4149098497756</ymax>
    </bndbox>
</object>
</annotation>
