<annotation verified="yes">
    <folder>Annotation</folder>
    <filename>gettyimages-544287287-612x612.jpg</filename>
    <path>Pothole-PascalVOC-export/Annotations/gettyimages-544287287-612x612.jpg</path>
    <source>
        <database>Unknown</database>
    </source>
    <size>
        <width>612</width>
        <height>408</height>
        <depth>3</depth>
    </size>
    <segmented>0</segmented>
    <object>
    <name>Pothole</name>
    <pose>Unspecified</pose>
    <truncated>0</truncated>
    <difficult>0</difficult>
    <bndbox>
        <xmin>101.57627221172571</xmin>
        <ymin>82.20534309364568</ymin>
        <xmax>538.3905192298776</xmax>
        <ymax>336.4486572990078</ymax>
    </bndbox>
</object>
</annotation>
