<annotation verified="yes">
    <folder>Annotation</folder>
    <filename>istockphoto-655985068-612x612.jpg</filename>
    <path>POTHOLES-PascalVOC-export/Annotations/istockphoto-655985068-612x612.jpg</path>
    <source>
        <database>Unknown</database>
    </source>
    <size>
        <width>612</width>
        <height>407</height>
        <depth>3</depth>
    </size>
    <segmented>0</segmented>
    <object>
    <name>Pothole</name>
    <pose>Unspecified</pose>
    <truncated>0</truncated>
    <difficult>0</difficult>
    <bndbox>
        <xmin>238.71273107563965</xmin>
        <ymin>264.54529213418766</ymin>
        <xmax>447.99508317037225</xmax>
        <ymax>366.23238232670997</ymax>
    </bndbox>
</object>
</annotation>
